icflow/__init__.py
icflow/main_cli.py
icflow/py.typed
icflow/config/__init__.py
icflow/config/config.py
icflow/data/__init__.py
icflow/data/cli.py
icflow/data/csv.py
icflow/data/data.py
icflow/data/dataset.py
icflow/data/netcdf.py
icflow/environment/__init__.py
icflow/environment/environment.py
icflow/session/__init__.py
icflow/session/app.py
icflow/session/auth.py
icflow/session/cli.py
icflow/session/report.py
icflow/sweep/__init__.py
icflow/sweep/config.py
icflow/sweep/reporter.py
icflow/sweep/session.py
icflow/utils/__init__.py
icflow/utils/profiler.py
icflow/web/__init__.py
icflow/web/app.py
icflow/web/dependencies.py
icflow/web/utils.py
icflow/web/views/__init__.py
icflow/web/views/dataset.py
icflow/web/views/product.py
icflow/web/views/unit.py
icflow/web/views/user.py
icflow-0.2.4.dist-info/licenses/LICENSE
icflow-0.2.4.dist-info/METADATA
icflow-0.2.4.dist-info/WHEEL
icflow-0.2.4.dist-info/entry_points.txt
icflow-0.2.4.dist-info/top_level.txt
icflow-0.2.4.dist-info/RECORD
